setup.py
./src/__init__.py
./src/command.py
./src/context.py
./src/exceptions.py
./src/whiteplanes.py
test/test_command.py
test/test_exceptions.py
test/test_execute.py
whiteplanes.egg-info/PKG-INFO
whiteplanes.egg-info/SOURCES.txt
whiteplanes.egg-info/dependency_links.txt
whiteplanes.egg-info/top_level.txt