Metadata-Version: 1.1
Name: whiteplanes
Version: 0.0.1
Summary: Whitespace interpreter written in Python
Home-page: UNKNOWN
Author: Takuya Katsurada
Author-email: mail@nutcrack.io
License: MIT License
Platform: UNKNOWN
Classifier: Programming Language :: Python :: 3.4
Classifier: Programming Language :: Python :: 3.5
Classifier: License :: OSI Approved :: MIT License
